foo/bar/data.py
foo/constants.py
primerpakete-0.0.0.dist-info/WHEEL
primerpakete-0.0.0.dist-info/METADATA
primerpakete-0.0.0.dist-info/RECORD
