Metadata-Version: 2.1
Name: primerpakete
Version: 0.0.0
Summary: prueba
Author: Your Name
Author-email: you@example.com
Requires-Python: >=3.8,<4.0
Classifier: Programming Language :: Python :: 3
Classifier: Programming Language :: Python :: 3.8
Classifier: Programming Language :: Python :: 3.9
Requires-Dist: pandas (==1.3.2)
